sym_metanet/__init__.py
sym_metanet/errors.py
sym_metanet/network.py
sym_metanet/views.py
sym_metanet/blocks/base.py
sym_metanet/blocks/destinations.py
sym_metanet/blocks/links.py
sym_metanet/blocks/nodes.py
sym_metanet/blocks/origins.py
sym_metanet/engines/__init__.py
sym_metanet/engines/casadi.py
sym_metanet/engines/core.py
sym_metanet/engines/numpy.py
sym_metanet/util/funcs.py
sym_metanet/util/types.py
sym_metanet-1.1.2.dist-info/licenses/LICENSE
sym_metanet-1.1.2.dist-info/METADATA
sym_metanet-1.1.2.dist-info/WHEEL
sym_metanet-1.1.2.dist-info/top_level.txt
sym_metanet-1.1.2.dist-info/RECORD
