Metadata-Version: 2.4
Name: sym_metanet
Version: 1.1.2
Summary: Symbolic Modelling of Highway Traffic Networks with METANET
Author-email: Filippo Airaldi <filippoairaldi@gmail.com>
License-Expression: MIT
Project-URL: Homepage, https://github.com/FilippoAiraldi/sym-metanet
Project-URL: Bug Tracker, https://github.com/FilippoAiraldi/sym-metanet/issues
Keywords: modelling-framework,highway-network,highway-traffic
Classifier: Programming Language :: Python
Classifier: Programming Language :: Python :: 3 :: Only
Classifier: Programming Language :: Python :: 3.9
Classifier: Programming Language :: Python :: 3.10
Classifier: Programming Language :: Python :: 3.11
Classifier: Programming Language :: Python :: 3.12
Classifier: Programming Language :: Python :: 3.13
Classifier: Operating System :: OS Independent
Classifier: Intended Audience :: Science/Research
Classifier: Topic :: Scientific/Engineering :: Mathematics
Requires-Python: >=3.9
License-File: LICENSE
Requires-Dist: networkx>=2.8.4
Dynamic: license-file
